LICENSE
README.rst
setup.cfg
setup.py
flask_ratify/__init__.py
flask_ratify/core.py
flask_ratify/decorator.py
flask_ratify/extension.py
flask_ratify/version.py
flask_ratify.egg-info/PKG-INFO
flask_ratify.egg-info/SOURCES.txt
flask_ratify.egg-info/dependency_links.txt
flask_ratify.egg-info/not-zip-safe
flask_ratify.egg-info/requires.txt
flask_ratify.egg-info/top_level.txt